disk_health_predictor/__init__.py
disk_health_predictor/_types.py
disk_health_predictor/classifiers/__init__.py
disk_health_predictor/classifiers/_base.py
disk_health_predictor/classifiers/_prophetstor.py
disk_health_predictor/classifiers/_redhat.py
disk_health_predictor/classifiers/_utils.py
disk_health_predictor/pretrained_models/prophetstor/config.json
disk_health_predictor/pretrained_models/prophetstor/svm_1.pkl
disk_health_predictor/pretrained_models/prophetstor/svm_10.pkl
disk_health_predictor/pretrained_models/prophetstor/svm_104.pkl
disk_health_predictor/pretrained_models/prophetstor/svm_105.pkl
disk_health_predictor/pretrained_models/prophetstor/svm_109.pkl
disk_health_predictor/pretrained_models/prophetstor/svm_112.pkl
disk_health_predictor/pretrained_models/prophetstor/svm_114.pkl
disk_health_predictor/pretrained_models/prophetstor/svm_115.pkl
disk_health_predictor/pretrained_models/prophetstor/svm_118.pkl
disk_health_predictor/pretrained_models/prophetstor/svm_119.pkl
disk_health_predictor/pretrained_models/prophetstor/svm_12.pkl
disk_health_predictor/pretrained_models/prophetstor/svm_120.pkl
disk_health_predictor/pretrained_models/prophetstor/svm_123.pkl
disk_health_predictor/pretrained_models/prophetstor/svm_124.pkl
disk_health_predictor/pretrained_models/prophetstor/svm_125.pkl
disk_health_predictor/pretrained_models/prophetstor/svm_128.pkl
disk_health_predictor/pretrained_models/prophetstor/svm_131.pkl
disk_health_predictor/pretrained_models/prophetstor/svm_134.pkl
disk_health_predictor/pretrained_models/prophetstor/svm_138.pkl
disk_health_predictor/pretrained_models/prophetstor/svm_14.pkl
disk_health_predictor/pretrained_models/prophetstor/svm_141.pkl
disk_health_predictor/pretrained_models/prophetstor/svm_145.pkl
disk_health_predictor/pretrained_models/prophetstor/svm_151.pkl
disk_health_predictor/pretrained_models/prophetstor/svm_16.pkl
disk_health_predictor/pretrained_models/prophetstor/svm_161.pkl
disk_health_predictor-0.0.2.dist-info/AUTHORS.rst
disk_health_predictor-0.0.2.dist-info/LICENSE.txt
disk_health_predictor-0.0.2.dist-info/METADATA
disk_health_predictor-0.0.2.dist-info/WHEEL
disk_health_predictor-0.0.2.dist-info/top_level.txt
disk_health_predictor-0.0.2.dist-info/RECORD
