Metadata-Version: 2.1
Name: disk-health-predictor
Version: 0.0.2
Summary: A collection of machine learning models to predict disk failure
Home-page: https://github.com/aicoe-aiops/disk-health-predictor
Author: Karanraj Chauhan
Author-email: kachau@redhat.com
License: MIT
Project-URL: Documentation, https://github.com/aicoe-aiops/disk-health-predictor
Project-URL: Source, https://github.com/aicoe-aiops/disk-health-predictor
Project-URL: Tracker, https://github.com/aicoe-aiops/disk-health-predictor/issues
Project-URL: Download, https://pypi.org/project/disk-health-predictor/#files
Platform: any
Classifier: Development Status :: 4 - Beta
Classifier: Programming Language :: Python
Requires-Python: <3.8
License-File: LICENSE.txt
License-File: AUTHORS.rst
Requires-Dist: importlib-metadata
Requires-Dist: numpy
Requires-Dist: Cython
Requires-Dist: scikit-learn (<0.22)
